{
  "version": 1,
  "updatedAt": "2026-06-14T00:17:40.912Z",
  "cycle": 667,
  "playerCount": 2,
  "benchmark": {
    "score": 673504.1875,
    "winRate": 1,
    "averageRank": 1,
    "averagePassengers": 439947.96875,
    "averagePassengerMargin": 228556.21875,
    "averageConnectedCities": 20,
    "averageMoney": 8296360.404664412,
    "timeoutRate": 0,
    "sampleCount": 32,
    "weights": {
      "vehiclePriorityBus": 56.92069311400076,
      "vehiclePriorityTrain": 147.6270636320979,
      "vehiclePriorityAir": -33.72638851461399,
      "claimRailBaseScore": 61.464493784609985,
      "claimAirBaseScore": 97.13751584557549,
      "claimPopulationPerMillionScore": 6.288080105598691,
      "claimNewCityBonus": 24,
      "claimFirstModeBonus": 18,
      "claimRailCostPenaltyPerMillion": 4.307945913321058,
      "claimPacificPreference": 0,
      "claimMountainPreference": 0,
      "claimSouthPreference": 5.839233425578902,
      "claimSoutheastPreference": 6.7253940512559245,
      "claimMidwestPreference": -0.6176278742828546,
      "claimNortheastPreference": 2.358612009723272,
      "claimSameRegionLinkBonus": -3.938759710207316,
      "claimNewRegionBonus": 0,
      "claimLongDistancePreference": 14.919571553064243,
      "buyBusOwnedCityBonus": 7.716007420864871,
      "buyTrainPotentialClaimBonus": 51.68084059856934,
      "buyTrainFallbackOwnedCityBonus": 3.9234573892982945,
      "buyTrainNoClaimPenalty": 25.26648701215163,
      "buyAirPotentialClaimBonus": 28.42695048809983,
      "buyAirFallbackOwnedCityBonus": 11.388636013958603,
      "buyAirNoClaimPenalty": 39.48746975517964,
      "buyDuplicateVehiclePenalty": 6.366012846446401,
      "buyFirstTrainBonus": 15.459284954937175,
      "buyFirstAirBonus": 26.422247604600017,
      "earlyExpansionMultiplier": 1.45,
      "midExpansionMultiplier": 1.1817034385865557,
      "lateExpansionMultiplier": 0.4528080216908296,
      "earlyPopulationMultiplier": 0.8,
      "midPopulationMultiplier": 0.27691409648396076,
      "latePopulationMultiplier": 1.267599105822488,
      "earlyReadyOperationsScore": 12.092547246853687,
      "midReadyOperationsScore": 143.91187764118825,
      "lateReadyOperationsScore": 228,
      "earlyClaimBudget": 2.188568762733439,
      "midClaimBudget": 5.1174798648050475,
      "lateClaimBudget": 0,
      "podSplitBaseScore": 31.487725528954922,
      "podCityCountScore": 17.700414639607903,
      "podPopulationPerMillionScore": 11.728738037680115,
      "podPopulationPerDistanceScore": 50.2512889808443,
      "podDemandScore": 2.2194584363461702,
      "podDemandPerMileScore": 5.930336809420722,
      "podNetRevenueScore": 17.912357214439126,
      "podAdditionalRoutePenalty": 5.394748211666832,
      "podRemoveCityBaseScore": 2.6287409673844064,
      "podRemovePassengersPerDistanceGainScore": 21.894760658931254,
      "podRemoveNetRevenueGainScore": 18.569295245355796,
      "drawRegionDeckSizeScore": 0,
      "drawRegionOwnedCityBonus": 10.027028334295256,
      "drawRegionOpponentCityPenalty": 1.8737123567344889,
      "drawRegionBigCityScarcityBonus": 7.159461230202946,
      "keepCityPopulationScore": 21.348629225373625,
      "keepCityNetworkProximityScore": 8.634750742616044,
      "keepCityPairCohesionScore": 0,
      "keepCityRegionMatchScore": 3.4350336559737715,
      "keepCityAdjacencyPotentialScore": 4.879891703484787,
      "claimAdjacentNetworkBonus": 11.550841047925253,
      "claimOpponentBlockPenalty": 1.472488754511708
    }
  },
  "training": {
    "generatedAt": "2026-06-14T00:17:39.866Z",
    "config": {
      "iterations": 10,
      "gamesPerCandidate": 12,
      "playerCount": 2,
      "baseSeed": 343500,
      "candidatesPerIteration": 5,
      "mutationSeed": 751659,
      "maxSteps": 1400,
      "outputPath": "C:\\git\\transport-game\\public\\training-results\\latest-2p.json",
      "mutableLeverKeys": [
        "vehiclePriorityBus",
        "vehiclePriorityTrain",
        "vehiclePriorityAir",
        "claimRailBaseScore",
        "claimAirBaseScore",
        "claimPopulationPerMillionScore",
        "claimRailCostPenaltyPerMillion",
        "claimSouthPreference",
        "claimSoutheastPreference",
        "claimMidwestPreference",
        "claimNortheastPreference",
        "claimSameRegionLinkBonus",
        "claimLongDistancePreference",
        "buyBusOwnedCityBonus",
        "buyTrainPotentialClaimBonus",
        "buyTrainFallbackOwnedCityBonus",
        "buyTrainNoClaimPenalty",
        "buyAirPotentialClaimBonus",
        "buyAirFallbackOwnedCityBonus",
        "buyAirNoClaimPenalty",
        "buyDuplicateVehiclePenalty",
        "buyFirstTrainBonus",
        "buyFirstAirBonus",
        "midExpansionMultiplier",
        "lateExpansionMultiplier",
        "midPopulationMultiplier",
        "latePopulationMultiplier",
        "earlyReadyOperationsScore",
        "midReadyOperationsScore",
        "earlyClaimBudget",
        "midClaimBudget",
        "lateClaimBudget",
        "podSplitBaseScore",
        "podCityCountScore",
        "podPopulationPerMillionScore",
        "podPopulationPerDistanceScore",
        "podDemandScore",
        "podDemandPerMileScore",
        "podNetRevenueScore",
        "podAdditionalRoutePenalty",
        "podRemoveCityBaseScore",
        "podRemovePassengersPerDistanceGainScore",
        "podRemoveNetRevenueGainScore",
        "drawRegionDeckSizeScore",
        "drawRegionOwnedCityBonus",
        "drawRegionOpponentCityPenalty",
        "drawRegionBigCityScarcityBonus",
        "keepCityPopulationScore",
        "keepCityNetworkProximityScore",
        "keepCityRegionMatchScore",
        "keepCityAdjacencyPotentialScore",
        "claimAdjacentNetworkBonus",
        "claimOpponentBlockPenalty"
      ],
      "frozenLeverKeys": [
        "claimFirstModeBonus",
        "claimMountainPreference",
        "claimPacificPreference",
        "claimNewCityBonus",
        "claimNewRegionBonus",
        "earlyExpansionMultiplier",
        "earlyPopulationMultiplier",
        "lateReadyOperationsScore",
        "podRemoveCityBaseScore",
        "earlyReadyOperationsScore",
        "midReadyOperationsScore",
        "podSplitBaseScore",
        "claimMidwestPreference",
        "claimNortheastPreference",
        "claimSoutheastPreference",
        "claimSouthPreference",
        "claimSameRegionLinkBonus",
        "podNetRevenueScore",
        "drawRegionOpponentCityPenalty",
        "podRemoveNetRevenueGainScore",
        "podRemovePassengersPerDistanceGainScore",
        "buyFirstAirBonus",
        "buyFirstTrainBonus",
        "buyAirNoClaimPenalty",
        "buyTrainNoClaimPenalty",
        "buyAirFallbackOwnedCityBonus",
        "buyTrainFallbackOwnedCityBonus",
        "midExpansionMultiplier",
        "lateExpansionMultiplier",
        "latePopulationMultiplier",
        "keepCityPairCohesionScore"
      ]
    },
    "baseline": {
      "score": 356429.9166666666,
      "winRate": 0.4166666666666667,
      "averageRank": 1.5833333333333333,
      "averagePassengers": 325652.3333333333,
      "averagePassengerMargin": 29356.75,
      "averageConnectedCities": 18.416666666666668,
      "averageMoney": 10010299.567662373,
      "timeoutRate": 0,
      "sampleCount": 12,
      "weights": {
        "vehiclePriorityBus": 32.01727513956969,
        "vehiclePriorityTrain": 165.15666565968922,
        "vehiclePriorityAir": -24.613826805366454,
        "claimRailBaseScore": 58.225552416521865,
        "claimAirBaseScore": 67.90655435180024,
        "claimPopulationPerMillionScore": 5.284967548370967,
        "claimNewCityBonus": 24,
        "claimFirstModeBonus": 18,
        "claimRailCostPenaltyPerMillion": 4.138835694000775,
        "claimPacificPreference": 0,
        "claimMountainPreference": 0,
        "claimSouthPreference": 5.839233425578902,
        "claimSoutheastPreference": 6.7253940512559245,
        "claimMidwestPreference": -0.6176278742828546,
        "claimNortheastPreference": 2.358612009723272,
        "claimSameRegionLinkBonus": -3.938759710207316,
        "claimNewRegionBonus": 0,
        "claimLongDistancePreference": 14.444531097901717,
        "buyBusOwnedCityBonus": 5.367726653606615,
        "buyTrainPotentialClaimBonus": 80.69220045689596,
        "buyTrainFallbackOwnedCityBonus": 3.9234573892982945,
        "buyTrainNoClaimPenalty": 25.26648701215163,
        "buyAirPotentialClaimBonus": 4.7243575763423005,
        "buyAirFallbackOwnedCityBonus": 11.388636013958603,
        "buyAirNoClaimPenalty": 39.48746975517964,
        "buyDuplicateVehiclePenalty": 6.58489027167744,
        "buyFirstTrainBonus": 15.459284954937175,
        "buyFirstAirBonus": 26.422247604600017,
        "earlyExpansionMultiplier": 1.45,
        "midExpansionMultiplier": 1.1817034385865557,
        "lateExpansionMultiplier": 0.4528080216908296,
        "earlyPopulationMultiplier": 0.8,
        "midPopulationMultiplier": 0.1,
        "latePopulationMultiplier": 1.267599105822488,
        "earlyReadyOperationsScore": 12.092547246853687,
        "midReadyOperationsScore": 143.91187764118825,
        "lateReadyOperationsScore": 228,
        "earlyClaimBudget": 1.8260318800311777,
        "midClaimBudget": 5.957322479057169,
        "lateClaimBudget": 0.3311970713444884,
        "podSplitBaseScore": 31.487725528954922,
        "podCityCountScore": 22.153181019694443,
        "podPopulationPerMillionScore": 12.402061118648227,
        "podPopulationPerDistanceScore": 46.84420215165509,
        "podDemandScore": 2.4949928095187293,
        "podDemandPerMileScore": 4.048746319750089,
        "podNetRevenueScore": 17.912357214439126,
        "podAdditionalRoutePenalty": 0.2146066168471079,
        "podRemoveCityBaseScore": 2.6287409673844064,
        "podRemovePassengersPerDistanceGainScore": 21.894760658931254,
        "podRemoveNetRevenueGainScore": 18.569295245355796,
        "drawRegionDeckSizeScore": 0,
        "drawRegionOwnedCityBonus": 9.193257133910311,
        "drawRegionOpponentCityPenalty": 1.8737123567344889,
        "drawRegionBigCityScarcityBonus": 8.739354584995095,
        "keepCityPopulationScore": 22.427358629230763,
        "keepCityNetworkProximityScore": 8.759994472341523,
        "keepCityPairCohesionScore": 0,
        "keepCityRegionMatchScore": 2.5960171833323926,
        "keepCityAdjacencyPotentialScore": 2.219549076931758,
        "claimAdjacentNetworkBonus": 10.92999646019501,
        "claimOpponentBlockPenalty": 4.485816838302546
      }
    },
    "history": [
      {
        "iteration": 1,
        "temperature": 1,
        "best": {
          "score": 356429.9166666666,
          "winRate": 0.4166666666666667,
          "averageRank": 1.5833333333333333,
          "averagePassengers": 325652.3333333333,
          "averagePassengerMargin": 29356.75,
          "averageConnectedCities": 18.416666666666668,
          "averageMoney": 10010299.567662373,
          "timeoutRate": 0,
          "sampleCount": 12,
          "weights": {
            "vehiclePriorityBus": 32.01727513956969,
            "vehiclePriorityTrain": 165.15666565968922,
            "vehiclePriorityAir": -24.613826805366454,
            "claimRailBaseScore": 58.225552416521865,
            "claimAirBaseScore": 67.90655435180024,
            "claimPopulationPerMillionScore": 5.284967548370967,
            "claimNewCityBonus": 24,
            "claimFirstModeBonus": 18,
            "claimRailCostPenaltyPerMillion": 4.138835694000775,
            "claimPacificPreference": 0,
            "claimMountainPreference": 0,
            "claimSouthPreference": 5.839233425578902,
            "claimSoutheastPreference": 6.7253940512559245,
            "claimMidwestPreference": -0.6176278742828546,
            "claimNortheastPreference": 2.358612009723272,
            "claimSameRegionLinkBonus": -3.938759710207316,
            "claimNewRegionBonus": 0,
            "claimLongDistancePreference": 14.444531097901717,
            "buyBusOwnedCityBonus": 5.367726653606615,
            "buyTrainPotentialClaimBonus": 80.69220045689596,
            "buyTrainFallbackOwnedCityBonus": 3.9234573892982945,
            "buyTrainNoClaimPenalty": 25.26648701215163,
            "buyAirPotentialClaimBonus": 4.7243575763423005,
            "buyAirFallbackOwnedCityBonus": 11.388636013958603,
            "buyAirNoClaimPenalty": 39.48746975517964,
            "buyDuplicateVehiclePenalty": 6.58489027167744,
            "buyFirstTrainBonus": 15.459284954937175,
            "buyFirstAirBonus": 26.422247604600017,
            "earlyExpansionMultiplier": 1.45,
            "midExpansionMultiplier": 1.1817034385865557,
            "lateExpansionMultiplier": 0.4528080216908296,
            "earlyPopulationMultiplier": 0.8,
            "midPopulationMultiplier": 0.1,
            "latePopulationMultiplier": 1.267599105822488,
            "earlyReadyOperationsScore": 12.092547246853687,
            "midReadyOperationsScore": 143.91187764118825,
            "lateReadyOperationsScore": 228,
            "earlyClaimBudget": 1.8260318800311777,
            "midClaimBudget": 5.957322479057169,
            "lateClaimBudget": 0.3311970713444884,
            "podSplitBaseScore": 31.487725528954922,
            "podCityCountScore": 22.153181019694443,
            "podPopulationPerMillionScore": 12.402061118648227,
            "podPopulationPerDistanceScore": 46.84420215165509,
            "podDemandScore": 2.4949928095187293,
            "podDemandPerMileScore": 4.048746319750089,
            "podNetRevenueScore": 17.912357214439126,
            "podAdditionalRoutePenalty": 0.2146066168471079,
            "podRemoveCityBaseScore": 2.6287409673844064,
            "podRemovePassengersPerDistanceGainScore": 21.894760658931254,
            "podRemoveNetRevenueGainScore": 18.569295245355796,
            "drawRegionDeckSizeScore": 0,
            "drawRegionOwnedCityBonus": 9.193257133910311,
            "drawRegionOpponentCityPenalty": 1.8737123567344889,
            "drawRegionBigCityScarcityBonus": 8.739354584995095,
            "keepCityPopulationScore": 22.427358629230763,
            "keepCityNetworkProximityScore": 8.759994472341523,
            "keepCityPairCohesionScore": 0,
            "keepCityRegionMatchScore": 2.5960171833323926,
            "keepCityAdjacencyPotentialScore": 2.219549076931758,
            "claimAdjacentNetworkBonus": 10.92999646019501,
            "claimOpponentBlockPenalty": 4.485816838302546
          }
        },
        "candidate": {
          "score": 286631.1666666667,
          "winRate": 0.5,
          "averageRank": 1.5,
          "averagePassengers": 313702.9166666667,
          "averagePassengerMargin": -28988.416666666668,
          "averageConnectedCities": 18.333333333333332,
          "averageMoney": 11589058.80662953,
          "timeoutRate": 0,
          "sampleCount": 12,
          "weights": {
            "vehiclePriorityBus": 29.755033001183918,
            "vehiclePriorityTrain": 165.0175884954565,
            "vehiclePriorityAir": -24.604088676734147,
            "claimRailBaseScore": 51.53734443255122,
            "claimAirBaseScore": 51.95657050167874,
            "claimPopulationPerMillionScore": 5.206679206032912,
            "claimNewCityBonus": 24,
            "claimFirstModeBonus": 18,
            "claimRailCostPenaltyPerMillion": 3.798510392953361,
            "claimPacificPreference": 0,
            "claimMountainPreference": 0,
            "claimSouthPreference": 5.839233425578902,
            "claimSoutheastPreference": 6.7253940512559245,
            "claimMidwestPreference": -0.6176278742828546,
            "claimNortheastPreference": 2.358612009723272,
            "claimSameRegionLinkBonus": -3.938759710207316,
            "claimNewRegionBonus": 0,
            "claimLongDistancePreference": 8.5963957122394,
            "buyBusOwnedCityBonus": 5.505398862787507,
            "buyTrainPotentialClaimBonus": 70.05412559039993,
            "buyTrainFallbackOwnedCityBonus": 3.9234573892982945,
            "buyTrainNoClaimPenalty": 25.26648701215163,
            "buyAirPotentialClaimBonus": -2.0984632873442015,
            "buyAirFallbackOwnedCityBonus": 11.388636013958603,
            "buyAirNoClaimPenalty": 39.48746975517964,
            "buyDuplicateVehiclePenalty": 9.177209350420899,
            "buyFirstTrainBonus": 15.459284954937175,
            "buyFirstAirBonus": 26.422247604600017,
            "earlyExpansionMultiplier": 1.45,
            "midExpansionMultiplier": 1.1817034385865557,
            "lateExpansionMultiplier": 0.4528080216908296,
            "earlyPopulationMultiplier": 0.8,
            "midPopulationMultiplier": 0.2943305866792798,
            "latePopulationMultiplier": 1.267599105822488,
            "earlyReadyOperationsScore": 12.092547246853687,
            "midReadyOperationsScore": 143.91187764118825,
            "lateReadyOperationsScore": 228,
            "earlyClaimBudget": 2.585552957883874,
            "midClaimBudget": 6.535673904529816,
            "lateClaimBudget": 0.909833576054209,
            "podSplitBaseScore": 31.487725528954922,
            "podCityCountScore": 20.875587613777157,
            "podPopulationPerMillionScore": 13.833485325702306,
            "podPopulationPerDistanceScore": 52.446387943944764,
            "podDemandScore": 3.8865860753315733,
            "podDemandPerMileScore": 4.503728209325809,
            "podNetRevenueScore": 17.912357214439126,
            "podAdditionalRoutePenalty": 1.840769170053194,
            "podRemoveCityBaseScore": 2.6287409673844064,
            "podRemovePassengersPerDistanceGainScore": 21.894760658931254,
            "podRemoveNetRevenueGainScore": 18.569295245355796,
            "drawRegionDeckSizeScore": 0.39805268961936235,
            "drawRegionOwnedCityBonus": 7.427989579239739,
            "drawRegionOpponentCityPenalty": 1.8737123567344889,
            "drawRegionBigCityScarcityBonus": 10.657348240423385,
            "keepCityPopulationScore": 20.647367882591094,
            "keepCityNetworkProximityScore": 10.236272926406846,
            "keepCityPairCohesionScore": 0,
            "keepCityRegionMatchScore": 4.137692601016411,
            "keepCityAdjacencyPotentialScore": 3.5232097369825675,
            "claimAdjacentNetworkBonus": 13.53944156037954,
            "claimOpponentBlockPenalty": 5.045922049404019
          }
        }
      },
      {
        "iteration": 2,
        "temperature": 0.9,
        "best": {
          "score": 360867.4166666666,
          "winRate": 0.5,
          "averageRank": 1.5,
          "averagePassengers": 345198.75,
          "averagePassengerMargin": 13710.333333333334,
          "averageConnectedCities": 19.166666666666668,
          "averageMoney": 17516643.515178356,
          "timeoutRate": 0,
          "sampleCount": 12,
          "weights": {
            "vehiclePriorityBus": 42.70156864334961,
            "vehiclePriorityTrain": 152.33142927241778,
            "vehiclePriorityAir": -15.38379393351662,
            "claimRailBaseScore": 61.53710573792811,
            "claimAirBaseScore": 85.5528453000422,
            "claimPopulationPerMillionScore": 7.366112499654899,
            "claimNewCityBonus": 24,
            "claimFirstModeBonus": 18,
            "claimRailCostPenaltyPerMillion": 5.015751769219245,
            "claimPacificPreference": 0,
            "claimMountainPreference": 0,
            "claimSouthPreference": 5.839233425578902,
            "claimSoutheastPreference": 6.7253940512559245,
            "claimMidwestPreference": -0.6176278742828546,
            "claimNortheastPreference": 2.358612009723272,
            "claimSameRegionLinkBonus": -3.938759710207316,
            "claimNewRegionBonus": 0,
            "claimLongDistancePreference": 12.209727659342542,
            "buyBusOwnedCityBonus": 4.704772522185913,
            "buyTrainPotentialClaimBonus": 68.66429783577202,
            "buyTrainFallbackOwnedCityBonus": 3.9234573892982945,
            "buyTrainNoClaimPenalty": 25.26648701215163,
            "buyAirPotentialClaimBonus": 8.692246872046963,
            "buyAirFallbackOwnedCityBonus": 11.388636013958603,
            "buyAirNoClaimPenalty": 39.48746975517964,
            "buyDuplicateVehiclePenalty": 9.31618021293617,
            "buyFirstTrainBonus": 15.459284954937175,
            "buyFirstAirBonus": 26.422247604600017,
            "earlyExpansionMultiplier": 1.45,
            "midExpansionMultiplier": 1.1817034385865557,
            "lateExpansionMultiplier": 0.4528080216908296,
            "earlyPopulationMultiplier": 0.8,
            "midPopulationMultiplier": 0.1,
            "latePopulationMultiplier": 1.267599105822488,
            "earlyReadyOperationsScore": 12.092547246853687,
            "midReadyOperationsScore": 143.91187764118825,
            "lateReadyOperationsScore": 228,
            "earlyClaimBudget": 2.382608312784532,
            "midClaimBudget": 5.8575022378648125,
            "lateClaimBudget": 0.12828077901051296,
            "podSplitBaseScore": 31.487725528954922,
            "podCityCountScore": 19.492818733014996,
            "podPopulationPerMillionScore": 11.493500161261137,
            "podPopulationPerDistanceScore": 50.017927720344495,
            "podDemandScore": 2.37101436498065,
            "podDemandPerMileScore": 5.060786978045243,
            "podNetRevenueScore": 17.912357214439126,
            "podAdditionalRoutePenalty": 1.9343910223021012,
            "podRemoveCityBaseScore": 2.6287409673844064,
            "podRemovePassengersPerDistanceGainScore": 21.894760658931254,
            "podRemoveNetRevenueGainScore": 18.569295245355796,
            "drawRegionDeckSizeScore": 0,
            "drawRegionOwnedCityBonus": 10.494666768485558,
            "drawRegionOpponentCityPenalty": 1.8737123567344889,
            "drawRegionBigCityScarcityBonus": 9.330571006215546,
            "keepCityPopulationScore": 22.922962753057835,
            "keepCityNetworkProximityScore": 9.784024330845014,
            "keepCityPairCohesionScore": 0,
            "keepCityRegionMatchScore": 3.410050844649473,
            "keepCityAdjacencyPotentialScore": 3.938271008266343,
            "claimAdjacentNetworkBonus": 9.322962298135584,
            "claimOpponentBlockPenalty": 4.073962338165277
          }
        },
        "candidate": {
          "score": 360867.4166666666,
          "winRate": 0.5,
          "averageRank": 1.5,
          "averagePassengers": 345198.75,
          "averagePassengerMargin": 13710.333333333334,
          "averageConnectedCities": 19.166666666666668,
          "averageMoney": 17516643.515178356,
          "timeoutRate": 0,
          "sampleCount": 12,
          "weights": {
            "vehiclePriorityBus": 42.70156864334961,
            "vehiclePriorityTrain": 152.33142927241778,
            "vehiclePriorityAir": -15.38379393351662,
            "claimRailBaseScore": 61.53710573792811,
            "claimAirBaseScore": 85.5528453000422,
            "claimPopulationPerMillionScore": 7.366112499654899,
            "claimNewCityBonus": 24,
            "claimFirstModeBonus": 18,
            "claimRailCostPenaltyPerMillion": 5.015751769219245,
            "claimPacificPreference": 0,
            "claimMountainPreference": 0,
            "claimSouthPreference": 5.839233425578902,
            "claimSoutheastPreference": 6.7253940512559245,
            "claimMidwestPreference": -0.6176278742828546,
            "claimNortheastPreference": 2.358612009723272,
            "claimSameRegionLinkBonus": -3.938759710207316,
            "claimNewRegionBonus": 0,
            "claimLongDistancePreference": 12.209727659342542,
            "buyBusOwnedCityBonus": 4.704772522185913,
            "buyTrainPotentialClaimBonus": 68.66429783577202,
            "buyTrainFallbackOwnedCityBonus": 3.9234573892982945,
            "buyTrainNoClaimPenalty": 25.26648701215163,
            "buyAirPotentialClaimBonus": 8.692246872046963,
            "buyAirFallbackOwnedCityBonus": 11.388636013958603,
            "buyAirNoClaimPenalty": 39.48746975517964,
            "buyDuplicateVehiclePenalty": 9.31618021293617,
            "buyFirstTrainBonus": 15.459284954937175,
            "buyFirstAirBonus": 26.422247604600017,
            "earlyExpansionMultiplier": 1.45,
            "midExpansionMultiplier": 1.1817034385865557,
            "lateExpansionMultiplier": 0.4528080216908296,
            "earlyPopulationMultiplier": 0.8,
            "midPopulationMultiplier": 0.1,
            "latePopulationMultiplier": 1.267599105822488,
            "earlyReadyOperationsScore": 12.092547246853687,
            "midReadyOperationsScore": 143.91187764118825,
            "lateReadyOperationsScore": 228,
            "earlyClaimBudget": 2.382608312784532,
            "midClaimBudget": 5.8575022378648125,
            "lateClaimBudget": 0.12828077901051296,
            "podSplitBaseScore": 31.487725528954922,
            "podCityCountScore": 19.492818733014996,
            "podPopulationPerMillionScore": 11.493500161261137,
            "podPopulationPerDistanceScore": 50.017927720344495,
            "podDemandScore": 2.37101436498065,
            "podDemandPerMileScore": 5.060786978045243,
            "podNetRevenueScore": 17.912357214439126,
            "podAdditionalRoutePenalty": 1.9343910223021012,
            "podRemoveCityBaseScore": 2.6287409673844064,
            "podRemovePassengersPerDistanceGainScore": 21.894760658931254,
            "podRemoveNetRevenueGainScore": 18.569295245355796,
            "drawRegionDeckSizeScore": 0,
            "drawRegionOwnedCityBonus": 10.494666768485558,
            "drawRegionOpponentCityPenalty": 1.8737123567344889,
            "drawRegionBigCityScarcityBonus": 9.330571006215546,
            "keepCityPopulationScore": 22.922962753057835,
            "keepCityNetworkProximityScore": 9.784024330845014,
            "keepCityPairCohesionScore": 0,
            "keepCityRegionMatchScore": 3.410050844649473,
            "keepCityAdjacencyPotentialScore": 3.938271008266343,
            "claimAdjacentNetworkBonus": 9.322962298135584,
            "claimOpponentBlockPenalty": 4.073962338165277
          }
        }
      },
      {
        "iteration": 3,
        "temperature": 0.8,
        "best": {
          "score": 387199.6666666667,
          "winRate": 0.5,
          "averageRank": 1.5,
          "averagePassengers": 362928.9166666667,
          "averagePassengerMargin": 22304.083333333332,
          "averageConnectedCities": 19.333333333333332,
          "averageMoney": 8574772.413451893,
          "timeoutRate": 0,
          "sampleCount": 12,
          "weights": {
            "vehiclePriorityBus": 56.07040012662431,
            "vehiclePriorityTrain": 154.1090077954278,
            "vehiclePriorityAir": -29.4252922034024,
            "claimRailBaseScore": 69.63827264190073,
            "claimAirBaseScore": 94.98180684825138,
            "claimPopulationPerMillionScore": 7.475365046568821,
            "claimNewCityBonus": 24,
            "claimFirstModeBonus": 18,
            "claimRailCostPenaltyPerMillion": 4.417927976150716,
            "claimPacificPreference": 0,
            "claimMountainPreference": 0,
            "claimSouthPreference": 5.839233425578902,
            "claimSoutheastPreference": 6.7253940512559245,
            "claimMidwestPreference": -0.6176278742828546,
            "claimNortheastPreference": 2.358612009723272,
            "claimSameRegionLinkBonus": -3.938759710207316,
            "claimNewRegionBonus": 0,
            "claimLongDistancePreference": 18.59920846771981,
            "buyBusOwnedCityBonus": 5.744244893525711,
            "buyTrainPotentialClaimBonus": 61.05877989852903,
            "buyTrainFallbackOwnedCityBonus": 3.9234573892982945,
            "buyTrainNoClaimPenalty": 25.26648701215163,
            "buyAirPotentialClaimBonus": 19.507558948406952,
            "buyAirFallbackOwnedCityBonus": 11.388636013958603,
            "buyAirNoClaimPenalty": 39.48746975517964,
            "buyDuplicateVehiclePenalty": 8.253404468438394,
            "buyFirstTrainBonus": 15.459284954937175,
            "buyFirstAirBonus": 26.422247604600017,
            "earlyExpansionMultiplier": 1.45,
            "midExpansionMultiplier": 1.1817034385865557,
            "lateExpansionMultiplier": 0.4528080216908296,
            "earlyPopulationMultiplier": 0.8,
            "midPopulationMultiplier": 0.1,
            "latePopulationMultiplier": 1.267599105822488,
            "earlyReadyOperationsScore": 12.092547246853687,
            "midReadyOperationsScore": 143.91187764118825,
            "lateReadyOperationsScore": 228,
            "earlyClaimBudget": 3.1360464729804787,
            "midClaimBudget": 5.441965191968759,
            "lateClaimBudget": 0.276244589350083,
            "podSplitBaseScore": 31.487725528954922,
            "podCityCountScore": 16.356077881612713,
            "podPopulationPerMillionScore": 12.130358804852541,
            "podPopulationPerDistanceScore": 52.52131957331939,
            "podDemandScore": 3.36300386636008,
            "podDemandPerMileScore": 5.378763104865092,
            "podNetRevenueScore": 17.912357214439126,
            "podAdditionalRoutePenalty": 2.2344468718542556,
            "podRemoveCityBaseScore": 2.6287409673844064,
            "podRemovePassengersPerDistanceGainScore": 21.894760658931254,
            "podRemoveNetRevenueGainScore": 18.569295245355796,
            "drawRegionDeckSizeScore": 0,
            "drawRegionOwnedCityBonus": 10.02501820089842,
            "drawRegionOpponentCityPenalty": 1.8737123567344889,
            "drawRegionBigCityScarcityBonus": 7.971472547925446,
            "keepCityPopulationScore": 22.638911498666165,
            "keepCityNetworkProximityScore": 8.393521909287111,
            "keepCityPairCohesionScore": 0,
            "keepCityRegionMatchScore": 3.6570263798038156,
            "keepCityAdjacencyPotentialScore": 4.213937632573975,
            "claimAdjacentNetworkBonus": 9.313182675729816,
            "claimOpponentBlockPenalty": 3.1986485018291413
          }
        },
        "candidate": {
          "score": 387199.6666666667,
          "winRate": 0.5,
          "averageRank": 1.5,
          "averagePassengers": 362928.9166666667,
          "averagePassengerMargin": 22304.083333333332,
          "averageConnectedCities": 19.333333333333332,
          "averageMoney": 8574772.413451893,
          "timeoutRate": 0,
          "sampleCount": 12,
          "weights": {
            "vehiclePriorityBus": 56.07040012662431,
            "vehiclePriorityTrain": 154.1090077954278,
            "vehiclePriorityAir": -29.4252922034024,
            "claimRailBaseScore": 69.63827264190073,
            "claimAirBaseScore": 94.98180684825138,
            "claimPopulationPerMillionScore": 7.475365046568821,
            "claimNewCityBonus": 24,
            "claimFirstModeBonus": 18,
            "claimRailCostPenaltyPerMillion": 4.417927976150716,
            "claimPacificPreference": 0,
            "claimMountainPreference": 0,
            "claimSouthPreference": 5.839233425578902,
            "claimSoutheastPreference": 6.7253940512559245,
            "claimMidwestPreference": -0.6176278742828546,
            "claimNortheastPreference": 2.358612009723272,
            "claimSameRegionLinkBonus": -3.938759710207316,
            "claimNewRegionBonus": 0,
            "claimLongDistancePreference": 18.59920846771981,
            "buyBusOwnedCityBonus": 5.744244893525711,
            "buyTrainPotentialClaimBonus": 61.05877989852903,
            "buyTrainFallbackOwnedCityBonus": 3.9234573892982945,
            "buyTrainNoClaimPenalty": 25.26648701215163,
            "buyAirPotentialClaimBonus": 19.507558948406952,
            "buyAirFallbackOwnedCityBonus": 11.388636013958603,
            "buyAirNoClaimPenalty": 39.48746975517964,
            "buyDuplicateVehiclePenalty": 8.253404468438394,
            "buyFirstTrainBonus": 15.459284954937175,
            "buyFirstAirBonus": 26.422247604600017,
            "earlyExpansionMultiplier": 1.45,
            "midExpansionMultiplier": 1.1817034385865557,
            "lateExpansionMultiplier": 0.4528080216908296,
            "earlyPopulationMultiplier": 0.8,
            "midPopulationMultiplier": 0.1,
            "latePopulationMultiplier": 1.267599105822488,
            "earlyReadyOperationsScore": 12.092547246853687,
            "midReadyOperationsScore": 143.91187764118825,
            "lateReadyOperationsScore": 228,
            "earlyClaimBudget": 3.1360464729804787,
            "midClaimBudget": 5.441965191968759,
            "lateClaimBudget": 0.276244589350083,
            "podSplitBaseScore": 31.487725528954922,
            "podCityCountScore": 16.356077881612713,
            "podPopulationPerMillionScore": 12.130358804852541,
            "podPopulationPerDistanceScore": 52.52131957331939,
            "podDemandScore": 3.36300386636008,
            "podDemandPerMileScore": 5.378763104865092,
            "podNetRevenueScore": 17.912357214439126,
            "podAdditionalRoutePenalty": 2.2344468718542556,
            "podRemoveCityBaseScore": 2.6287409673844064,
            "podRemovePassengersPerDistanceGainScore": 21.894760658931254,
            "podRemoveNetRevenueGainScore": 18.569295245355796,
            "drawRegionDeckSizeScore": 0,
            "drawRegionOwnedCityBonus": 10.02501820089842,
            "drawRegionOpponentCityPenalty": 1.8737123567344889,
            "drawRegionBigCityScarcityBonus": 7.971472547925446,
            "keepCityPopulationScore": 22.638911498666165,
            "keepCityNetworkProximityScore": 8.393521909287111,
            "keepCityPairCohesionScore": 0,
            "keepCityRegionMatchScore": 3.6570263798038156,
            "keepCityAdjacencyPotentialScore": 4.213937632573975,
            "claimAdjacentNetworkBonus": 9.313182675729816,
            "claimOpponentBlockPenalty": 3.1986485018291413
          }
        }
      },
      {
        "iteration": 4,
        "temperature": 0.7,
        "best": {
          "score": 389128.75,
          "winRate": 0.5833333333333334,
          "averageRank": 1.4166666666666667,
          "averagePassengers": 336565.8333333333,
          "averagePassengerMargin": 50112.916666666664,
          "averageConnectedCities": 19,
          "averageMoney": 8354085.151450891,
          "timeoutRate": 0,
          "sampleCount": 12,
          "weights": {
            "vehiclePriorityBus": 49.99130730868449,
            "vehiclePriorityTrain": 146.71632183091052,
            "vehiclePriorityAir": -38.0845879593997,
            "claimRailBaseScore": 68.42024992734547,
            "claimAirBaseScore": 101.70314126578823,
            "claimPopulationPerMillionScore": 6.958874719956564,
            "claimNewCityBonus": 24,
            "claimFirstModeBonus": 18,
            "claimRailCostPenaltyPerMillion": 4.028323843202273,
            "claimPacificPreference": 0,
            "claimMountainPreference": 0,
            "claimSouthPreference": 5.839233425578902,
            "claimSoutheastPreference": 6.7253940512559245,
            "claimMidwestPreference": -0.6176278742828546,
            "claimNortheastPreference": 2.358612009723272,
            "claimSameRegionLinkBonus": -3.938759710207316,
            "claimNewRegionBonus": 0,
            "claimLongDistancePreference": 14.80783100490059,
            "buyBusOwnedCityBonus": 7.071721797508172,
            "buyTrainPotentialClaimBonus": 54.76291234601391,
            "buyTrainFallbackOwnedCityBonus": 3.9234573892982945,
            "buyTrainNoClaimPenalty": 25.26648701215163,
            "buyAirPotentialClaimBonus": 24.56859377459623,
            "buyAirFallbackOwnedCityBonus": 11.388636013958603,
            "buyAirNoClaimPenalty": 39.48746975517964,
            "buyDuplicateVehiclePenalty": 7.4933254247073,
            "buyFirstTrainBonus": 15.459284954937175,
            "buyFirstAirBonus": 26.422247604600017,
            "earlyExpansionMultiplier": 1.45,
            "midExpansionMultiplier": 1.1817034385865557,
            "lateExpansionMultiplier": 0.4528080216908296,
            "earlyPopulationMultiplier": 0.8,
            "midPopulationMultiplier": 0.16913579939864576,
            "latePopulationMultiplier": 1.267599105822488,
            "earlyReadyOperationsScore": 12.092547246853687,
            "midReadyOperationsScore": 143.91187764118825,
            "lateReadyOperationsScore": 228,
            "earlyClaimBudget": 2.563810855845759,
            "midClaimBudget": 5.021825280151372,
            "lateClaimBudget": 0.059021626123123894,
            "podSplitBaseScore": 31.487725528954922,
            "podCityCountScore": 18.428283959896202,
            "podPopulationPerMillionScore": 12.696851176020528,
            "podPopulationPerDistanceScore": 48.775069610814434,
            "podDemandScore": 2.8513889145427616,
            "podDemandPerMileScore": 5.727283353248375,
            "podNetRevenueScore": 17.912357214439126,
            "podAdditionalRoutePenalty": 4.039782890692244,
            "podRemoveCityBaseScore": 2.6287409673844064,
            "podRemovePassengersPerDistanceGainScore": 21.894760658931254,
            "podRemoveNetRevenueGainScore": 18.569295245355796,
            "drawRegionDeckSizeScore": 0,
            "drawRegionOwnedCityBonus": 9.978679179927212,
            "drawRegionOpponentCityPenalty": 1.8737123567344889,
            "drawRegionBigCityScarcityBonus": 7.840304562799069,
            "keepCityPopulationScore": 22.34247557535058,
            "keepCityNetworkProximityScore": 8.706828396545635,
            "keepCityPairCohesionScore": 0,
            "keepCityRegionMatchScore": 3.4262674593056235,
            "keepCityAdjacencyPotentialScore": 3.8146347280798683,
            "claimAdjacentNetworkBonus": 11.073220154022177,
            "claimOpponentBlockPenalty": 2.5252257331170975
          }
        },
        "candidate": {
          "score": 389128.75,
          "winRate": 0.5833333333333334,
          "averageRank": 1.4166666666666667,
          "averagePassengers": 336565.8333333333,
          "averagePassengerMargin": 50112.916666666664,
          "averageConnectedCities": 19,
          "averageMoney": 8354085.151450891,
          "timeoutRate": 0,
          "sampleCount": 12,
          "weights": {
            "vehiclePriorityBus": 49.99130730868449,
            "vehiclePriorityTrain": 146.71632183091052,
            "vehiclePriorityAir": -38.0845879593997,
            "claimRailBaseScore": 68.42024992734547,
            "claimAirBaseScore": 101.70314126578823,
            "claimPopulationPerMillionScore": 6.958874719956564,
            "claimNewCityBonus": 24,
            "claimFirstModeBonus": 18,
            "claimRailCostPenaltyPerMillion": 4.028323843202273,
            "claimPacificPreference": 0,
            "claimMountainPreference": 0,
            "claimSouthPreference": 5.839233425578902,
            "claimSoutheastPreference": 6.7253940512559245,
            "claimMidwestPreference": -0.6176278742828546,
            "claimNortheastPreference": 2.358612009723272,
            "claimSameRegionLinkBonus": -3.938759710207316,
            "claimNewRegionBonus": 0,
            "claimLongDistancePreference": 14.80783100490059,
            "buyBusOwnedCityBonus": 7.071721797508172,
            "buyTrainPotentialClaimBonus": 54.76291234601391,
            "buyTrainFallbackOwnedCityBonus": 3.9234573892982945,
            "buyTrainNoClaimPenalty": 25.26648701215163,
            "buyAirPotentialClaimBonus": 24.56859377459623,
            "buyAirFallbackOwnedCityBonus": 11.388636013958603,
            "buyAirNoClaimPenalty": 39.48746975517964,
            "buyDuplicateVehiclePenalty": 7.4933254247073,
            "buyFirstTrainBonus": 15.459284954937175,
            "buyFirstAirBonus": 26.422247604600017,
            "earlyExpansionMultiplier": 1.45,
            "midExpansionMultiplier": 1.1817034385865557,
            "lateExpansionMultiplier": 0.4528080216908296,
            "earlyPopulationMultiplier": 0.8,
            "midPopulationMultiplier": 0.16913579939864576,
            "latePopulationMultiplier": 1.267599105822488,
            "earlyReadyOperationsScore": 12.092547246853687,
            "midReadyOperationsScore": 143.91187764118825,
            "lateReadyOperationsScore": 228,
            "earlyClaimBudget": 2.563810855845759,
            "midClaimBudget": 5.021825280151372,
            "lateClaimBudget": 0.059021626123123894,
            "podSplitBaseScore": 31.487725528954922,
            "podCityCountScore": 18.428283959896202,
            "podPopulationPerMillionScore": 12.696851176020528,
            "podPopulationPerDistanceScore": 48.775069610814434,
            "podDemandScore": 2.8513889145427616,
            "podDemandPerMileScore": 5.727283353248375,
            "podNetRevenueScore": 17.912357214439126,
            "podAdditionalRoutePenalty": 4.039782890692244,
            "podRemoveCityBaseScore": 2.6287409673844064,
            "podRemovePassengersPerDistanceGainScore": 21.894760658931254,
            "podRemoveNetRevenueGainScore": 18.569295245355796,
            "drawRegionDeckSizeScore": 0,
            "drawRegionOwnedCityBonus": 9.978679179927212,
            "drawRegionOpponentCityPenalty": 1.8737123567344889,
            "drawRegionBigCityScarcityBonus": 7.840304562799069,
            "keepCityPopulationScore": 22.34247557535058,
            "keepCityNetworkProximityScore": 8.706828396545635,
            "keepCityPairCohesionScore": 0,
            "keepCityRegionMatchScore": 3.4262674593056235,
            "keepCityAdjacencyPotentialScore": 3.8146347280798683,
            "claimAdjacentNetworkBonus": 11.073220154022177,
            "claimOpponentBlockPenalty": 2.5252257331170975
          }
        }
      },
      {
        "iteration": 5,
        "temperature": 0.6,
        "best": {
          "score": 405971.5833333334,
          "winRate": 0.5833333333333334,
          "averageRank": 1.4166666666666667,
          "averagePassengers": 345683.9166666667,
          "averagePassengerMargin": 57837.666666666664,
          "averageConnectedCities": 19,
          "averageMoney": 9131192.912387757,
          "timeoutRate": 0,
          "sampleCount": 12,
          "weights": {
            "vehiclePriorityBus": 56.92069311400076,
            "vehiclePriorityTrain": 147.6270636320979,
            "vehiclePriorityAir": -33.72638851461399,
            "claimRailBaseScore": 61.464493784609985,
            "claimAirBaseScore": 97.13751584557549,
            "claimPopulationPerMillionScore": 6.288080105598691,
            "claimNewCityBonus": 24,
            "claimFirstModeBonus": 18,
            "claimRailCostPenaltyPerMillion": 4.307945913321058,
            "claimPacificPreference": 0,
            "claimMountainPreference": 0,
            "claimSouthPreference": 5.839233425578902,
            "claimSoutheastPreference": 6.7253940512559245,
            "claimMidwestPreference": -0.6176278742828546,
            "claimNortheastPreference": 2.358612009723272,
            "claimSameRegionLinkBonus": -3.938759710207316,
            "claimNewRegionBonus": 0,
            "claimLongDistancePreference": 14.919571553064243,
            "buyBusOwnedCityBonus": 7.716007420864871,
            "buyTrainPotentialClaimBonus": 51.68084059856934,
            "buyTrainFallbackOwnedCityBonus": 3.9234573892982945,
            "buyTrainNoClaimPenalty": 25.26648701215163,
            "buyAirPotentialClaimBonus": 28.42695048809983,
            "buyAirFallbackOwnedCityBonus": 11.388636013958603,
            "buyAirNoClaimPenalty": 39.48746975517964,
            "buyDuplicateVehiclePenalty": 6.366012846446401,
            "buyFirstTrainBonus": 15.459284954937175,
            "buyFirstAirBonus": 26.422247604600017,
            "earlyExpansionMultiplier": 1.45,
            "midExpansionMultiplier": 1.1817034385865557,
            "lateExpansionMultiplier": 0.4528080216908296,
            "earlyPopulationMultiplier": 0.8,
            "midPopulationMultiplier": 0.27691409648396076,
            "latePopulationMultiplier": 1.267599105822488,
            "earlyReadyOperationsScore": 12.092547246853687,
            "midReadyOperationsScore": 143.91187764118825,
            "lateReadyOperationsScore": 228,
            "earlyClaimBudget": 2.188568762733439,
            "midClaimBudget": 5.1174798648050475,
            "lateClaimBudget": 0,
            "podSplitBaseScore": 31.487725528954922,
            "podCityCountScore": 17.700414639607903,
            "podPopulationPerMillionScore": 11.728738037680115,
            "podPopulationPerDistanceScore": 50.2512889808443,
            "podDemandScore": 2.2194584363461702,
            "podDemandPerMileScore": 5.930336809420722,
            "podNetRevenueScore": 17.912357214439126,
            "podAdditionalRoutePenalty": 5.394748211666832,
            "podRemoveCityBaseScore": 2.6287409673844064,
            "podRemovePassengersPerDistanceGainScore": 21.894760658931254,
            "podRemoveNetRevenueGainScore": 18.569295245355796,
            "drawRegionDeckSizeScore": 0,
            "drawRegionOwnedCityBonus": 10.027028334295256,
            "drawRegionOpponentCityPenalty": 1.8737123567344889,
            "drawRegionBigCityScarcityBonus": 7.159461230202946,
            "keepCityPopulationScore": 21.348629225373625,
            "keepCityNetworkProximityScore": 8.634750742616044,
            "keepCityPairCohesionScore": 0,
            "keepCityRegionMatchScore": 3.4350336559737715,
            "keepCityAdjacencyPotentialScore": 4.879891703484787,
            "claimAdjacentNetworkBonus": 11.550841047925253,
            "claimOpponentBlockPenalty": 1.472488754511708
          }
        },
        "candidate": {
          "score": 405971.5833333334,
          "winRate": 0.5833333333333334,
          "averageRank": 1.4166666666666667,
          "averagePassengers": 345683.9166666667,
          "averagePassengerMargin": 57837.666666666664,
          "averageConnectedCities": 19,
          "averageMoney": 9131192.912387757,
          "timeoutRate": 0,
          "sampleCount": 12,
          "weights": {
            "vehiclePriorityBus": 56.92069311400076,
            "vehiclePriorityTrain": 147.6270636320979,
            "vehiclePriorityAir": -33.72638851461399,
            "claimRailBaseScore": 61.464493784609985,
            "claimAirBaseScore": 97.13751584557549,
            "claimPopulationPerMillionScore": 6.288080105598691,
            "claimNewCityBonus": 24,
            "claimFirstModeBonus": 18,
            "claimRailCostPenaltyPerMillion": 4.307945913321058,
            "claimPacificPreference": 0,
            "claimMountainPreference": 0,
            "claimSouthPreference": 5.839233425578902,
            "claimSoutheastPreference": 6.7253940512559245,
            "claimMidwestPreference": -0.6176278742828546,
            "claimNortheastPreference": 2.358612009723272,
            "claimSameRegionLinkBonus": -3.938759710207316,
            "claimNewRegionBonus": 0,
            "claimLongDistancePreference": 14.919571553064243,
            "buyBusOwnedCityBonus": 7.716007420864871,
            "buyTrainPotentialClaimBonus": 51.68084059856934,
            "buyTrainFallbackOwnedCityBonus": 3.9234573892982945,
            "buyTrainNoClaimPenalty": 25.26648701215163,
            "buyAirPotentialClaimBonus": 28.42695048809983,
            "buyAirFallbackOwnedCityBonus": 11.388636013958603,
            "buyAirNoClaimPenalty": 39.48746975517964,
            "buyDuplicateVehiclePenalty": 6.366012846446401,
            "buyFirstTrainBonus": 15.459284954937175,
            "buyFirstAirBonus": 26.422247604600017,
            "earlyExpansionMultiplier": 1.45,
            "midExpansionMultiplier": 1.1817034385865557,
            "lateExpansionMultiplier": 0.4528080216908296,
            "earlyPopulationMultiplier": 0.8,
            "midPopulationMultiplier": 0.27691409648396076,
            "latePopulationMultiplier": 1.267599105822488,
            "earlyReadyOperationsScore": 12.092547246853687,
            "midReadyOperationsScore": 143.91187764118825,
            "lateReadyOperationsScore": 228,
            "earlyClaimBudget": 2.188568762733439,
            "midClaimBudget": 5.1174798648050475,
            "lateClaimBudget": 0,
            "podSplitBaseScore": 31.487725528954922,
            "podCityCountScore": 17.700414639607903,
            "podPopulationPerMillionScore": 11.728738037680115,
            "podPopulationPerDistanceScore": 50.2512889808443,
            "podDemandScore": 2.2194584363461702,
            "podDemandPerMileScore": 5.930336809420722,
            "podNetRevenueScore": 17.912357214439126,
            "podAdditionalRoutePenalty": 5.394748211666832,
            "podRemoveCityBaseScore": 2.6287409673844064,
            "podRemovePassengersPerDistanceGainScore": 21.894760658931254,
            "podRemoveNetRevenueGainScore": 18.569295245355796,
            "drawRegionDeckSizeScore": 0,
            "drawRegionOwnedCityBonus": 10.027028334295256,
            "drawRegionOpponentCityPenalty": 1.8737123567344889,
            "drawRegionBigCityScarcityBonus": 7.159461230202946,
            "keepCityPopulationScore": 21.348629225373625,
            "keepCityNetworkProximityScore": 8.634750742616044,
            "keepCityPairCohesionScore": 0,
            "keepCityRegionMatchScore": 3.4350336559737715,
            "keepCityAdjacencyPotentialScore": 4.879891703484787,
            "claimAdjacentNetworkBonus": 11.550841047925253,
            "claimOpponentBlockPenalty": 1.472488754511708
          }
        }
      },
      {
        "iteration": 6,
        "temperature": 0.5,
        "best": {
          "score": 405971.5833333334,
          "winRate": 0.5833333333333334,
          "averageRank": 1.4166666666666667,
          "averagePassengers": 345683.9166666667,
          "averagePassengerMargin": 57837.666666666664,
          "averageConnectedCities": 19,
          "averageMoney": 9131192.912387757,
          "timeoutRate": 0,
          "sampleCount": 12,
          "weights": {
            "vehiclePriorityBus": 56.92069311400076,
            "vehiclePriorityTrain": 147.6270636320979,
            "vehiclePriorityAir": -33.72638851461399,
            "claimRailBaseScore": 61.464493784609985,
            "claimAirBaseScore": 97.13751584557549,
            "claimPopulationPerMillionScore": 6.288080105598691,
            "claimNewCityBonus": 24,
            "claimFirstModeBonus": 18,
            "claimRailCostPenaltyPerMillion": 4.307945913321058,
            "claimPacificPreference": 0,
            "claimMountainPreference": 0,
            "claimSouthPreference": 5.839233425578902,
            "claimSoutheastPreference": 6.7253940512559245,
            "claimMidwestPreference": -0.6176278742828546,
            "claimNortheastPreference": 2.358612009723272,
            "claimSameRegionLinkBonus": -3.938759710207316,
            "claimNewRegionBonus": 0,
            "claimLongDistancePreference": 14.919571553064243,
            "buyBusOwnedCityBonus": 7.716007420864871,
            "buyTrainPotentialClaimBonus": 51.68084059856934,
            "buyTrainFallbackOwnedCityBonus": 3.9234573892982945,
            "buyTrainNoClaimPenalty": 25.26648701215163,
            "buyAirPotentialClaimBonus": 28.42695048809983,
            "buyAirFallbackOwnedCityBonus": 11.388636013958603,
            "buyAirNoClaimPenalty": 39.48746975517964,
            "buyDuplicateVehiclePenalty": 6.366012846446401,
            "buyFirstTrainBonus": 15.459284954937175,
            "buyFirstAirBonus": 26.422247604600017,
            "earlyExpansionMultiplier": 1.45,
            "midExpansionMultiplier": 1.1817034385865557,
            "lateExpansionMultiplier": 0.4528080216908296,
            "earlyPopulationMultiplier": 0.8,
            "midPopulationMultiplier": 0.27691409648396076,
            "latePopulationMultiplier": 1.267599105822488,
            "earlyReadyOperationsScore": 12.092547246853687,
            "midReadyOperationsScore": 143.91187764118825,
            "lateReadyOperationsScore": 228,
            "earlyClaimBudget": 2.188568762733439,
            "midClaimBudget": 5.1174798648050475,
            "lateClaimBudget": 0,
            "podSplitBaseScore": 31.487725528954922,
            "podCityCountScore": 17.700414639607903,
            "podPopulationPerMillionScore": 11.728738037680115,
            "podPopulationPerDistanceScore": 50.2512889808443,
            "podDemandScore": 2.2194584363461702,
            "podDemandPerMileScore": 5.930336809420722,
            "podNetRevenueScore": 17.912357214439126,
            "podAdditionalRoutePenalty": 5.394748211666832,
            "podRemoveCityBaseScore": 2.6287409673844064,
            "podRemovePassengersPerDistanceGainScore": 21.894760658931254,
            "podRemoveNetRevenueGainScore": 18.569295245355796,
            "drawRegionDeckSizeScore": 0,
            "drawRegionOwnedCityBonus": 10.027028334295256,
            "drawRegionOpponentCityPenalty": 1.8737123567344889,
            "drawRegionBigCityScarcityBonus": 7.159461230202946,
            "keepCityPopulationScore": 21.348629225373625,
            "keepCityNetworkProximityScore": 8.634750742616044,
            "keepCityPairCohesionScore": 0,
            "keepCityRegionMatchScore": 3.4350336559737715,
            "keepCityAdjacencyPotentialScore": 4.879891703484787,
            "claimAdjacentNetworkBonus": 11.550841047925253,
            "claimOpponentBlockPenalty": 1.472488754511708
          }
        },
        "candidate": {
          "score": 390840.0833333333,
          "winRate": 0.5833333333333334,
          "averageRank": 1.4166666666666667,
          "averagePassengers": 337556.0833333333,
          "averagePassengerMargin": 50834,
          "averageConnectedCities": 19,
          "averageMoney": 8606915.943063566,
          "timeoutRate": 0,
          "sampleCount": 12,
          "weights": {
            "vehiclePriorityBus": 65.0365404044943,
            "vehiclePriorityTrain": 149.1390071302586,
            "vehiclePriorityAir": -34.125978464832784,
            "claimRailBaseScore": 63.77493426904435,
            "claimAirBaseScore": 85.747290556186,
            "claimPopulationPerMillionScore": 6.697046496131132,
            "claimNewCityBonus": 24,
            "claimFirstModeBonus": 18,
            "claimRailCostPenaltyPerMillion": 4.756234266946743,
            "claimPacificPreference": 0,
            "claimMountainPreference": 0,
            "claimSouthPreference": 5.839233425578902,
            "claimSoutheastPreference": 6.7253940512559245,
            "claimMidwestPreference": -0.6176278742828546,
            "claimNortheastPreference": 2.358612009723272,
            "claimSameRegionLinkBonus": -3.938759710207316,
            "claimNewRegionBonus": 0,
            "claimLongDistancePreference": 16.085722080139178,
            "buyBusOwnedCityBonus": 7.274700836815855,
            "buyTrainPotentialClaimBonus": 56.01925957497311,
            "buyTrainFallbackOwnedCityBonus": 3.9234573892982945,
            "buyTrainNoClaimPenalty": 25.26648701215163,
            "buyAirPotentialClaimBonus": 35.371880737924954,
            "buyAirFallbackOwnedCityBonus": 11.388636013958603,
            "buyAirNoClaimPenalty": 39.48746975517964,
            "buyDuplicateVehiclePenalty": 7.852123278519875,
            "buyFirstTrainBonus": 15.459284954937175,
            "buyFirstAirBonus": 26.422247604600017,
            "earlyExpansionMultiplier": 1.45,
            "midExpansionMultiplier": 1.1817034385865557,
            "lateExpansionMultiplier": 0.4528080216908296,
            "earlyPopulationMultiplier": 0.8,
            "midPopulationMultiplier": 0.3365519199986011,
            "latePopulationMultiplier": 1.267599105822488,
            "earlyReadyOperationsScore": 12.092547246853687,
            "midReadyOperationsScore": 143.91187764118825,
            "lateReadyOperationsScore": 228,
            "earlyClaimBudget": 2.6443120839510357,
            "midClaimBudget": 5.063832202059259,
            "lateClaimBudget": 0,
            "podSplitBaseScore": 31.487725528954922,
            "podCityCountScore": 17.166738289118644,
            "podPopulationPerMillionScore": 10.96038424391004,
            "podPopulationPerDistanceScore": 48.358678568753284,
            "podDemandScore": 2.4688888529637127,
            "podDemandPerMileScore": 6.677890595217931,
            "podNetRevenueScore": 17.912357214439126,
            "podAdditionalRoutePenalty": 5.77626019512851,
            "podRemoveCityBaseScore": 2.6287409673844064,
            "podRemovePassengersPerDistanceGainScore": 21.894760658931254,
            "podRemoveNetRevenueGainScore": 18.569295245355796,
            "drawRegionDeckSizeScore": 0,
            "drawRegionOwnedCityBonus": 10.165213251454635,
            "drawRegionOpponentCityPenalty": 1.8737123567344889,
            "drawRegionBigCityScarcityBonus": 6.200436560134771,
            "keepCityPopulationScore": 21.854155154761283,
            "keepCityNetworkProximityScore": 8.128104368375526,
            "keepCityPairCohesionScore": 0,
            "keepCityRegionMatchScore": 3.1936451296942923,
            "keepCityAdjacencyPotentialScore": 5.368458332142068,
            "claimAdjacentNetworkBonus": 10.463135501866539,
            "claimOpponentBlockPenalty": 1.0238079327055156
          }
        }
      },
      {
        "iteration": 7,
        "temperature": 0.4,
        "best": {
          "score": 405971.5833333334,
          "winRate": 0.5833333333333334,
          "averageRank": 1.4166666666666667,
          "averagePassengers": 345683.9166666667,
          "averagePassengerMargin": 57837.666666666664,
          "averageConnectedCities": 19,
          "averageMoney": 9131192.912387757,
          "timeoutRate": 0,
          "sampleCount": 12,
          "weights": {
            "vehiclePriorityBus": 56.92069311400076,
            "vehiclePriorityTrain": 147.6270636320979,
            "vehiclePriorityAir": -33.72638851461399,
            "claimRailBaseScore": 61.464493784609985,
            "claimAirBaseScore": 97.13751584557549,
            "claimPopulationPerMillionScore": 6.288080105598691,
            "claimNewCityBonus": 24,
            "claimFirstModeBonus": 18,
            "claimRailCostPenaltyPerMillion": 4.307945913321058,
            "claimPacificPreference": 0,
            "claimMountainPreference": 0,
            "claimSouthPreference": 5.839233425578902,
            "claimSoutheastPreference": 6.7253940512559245,
            "claimMidwestPreference": -0.6176278742828546,
            "claimNortheastPreference": 2.358612009723272,
            "claimSameRegionLinkBonus": -3.938759710207316,
            "claimNewRegionBonus": 0,
            "claimLongDistancePreference": 14.919571553064243,
            "buyBusOwnedCityBonus": 7.716007420864871,
            "buyTrainPotentialClaimBonus": 51.68084059856934,
            "buyTrainFallbackOwnedCityBonus": 3.9234573892982945,
            "buyTrainNoClaimPenalty": 25.26648701215163,
            "buyAirPotentialClaimBonus": 28.42695048809983,
            "buyAirFallbackOwnedCityBonus": 11.388636013958603,
            "buyAirNoClaimPenalty": 39.48746975517964,
            "buyDuplicateVehiclePenalty": 6.366012846446401,
            "buyFirstTrainBonus": 15.459284954937175,
            "buyFirstAirBonus": 26.422247604600017,
            "earlyExpansionMultiplier": 1.45,
            "midExpansionMultiplier": 1.1817034385865557,
            "lateExpansionMultiplier": 0.4528080216908296,
            "earlyPopulationMultiplier": 0.8,
            "midPopulationMultiplier": 0.27691409648396076,
            "latePopulationMultiplier": 1.267599105822488,
            "earlyReadyOperationsScore": 12.092547246853687,
            "midReadyOperationsScore": 143.91187764118825,
            "lateReadyOperationsScore": 228,
            "earlyClaimBudget": 2.188568762733439,
            "midClaimBudget": 5.1174798648050475,
            "lateClaimBudget": 0,
            "podSplitBaseScore": 31.487725528954922,
            "podCityCountScore": 17.700414639607903,
            "podPopulationPerMillionScore": 11.728738037680115,
            "podPopulationPerDistanceScore": 50.2512889808443,
            "podDemandScore": 2.2194584363461702,
            "podDemandPerMileScore": 5.930336809420722,
            "podNetRevenueScore": 17.912357214439126,
            "podAdditionalRoutePenalty": 5.394748211666832,
            "podRemoveCityBaseScore": 2.6287409673844064,
            "podRemovePassengersPerDistanceGainScore": 21.894760658931254,
            "podRemoveNetRevenueGainScore": 18.569295245355796,
            "drawRegionDeckSizeScore": 0,
            "drawRegionOwnedCityBonus": 10.027028334295256,
            "drawRegionOpponentCityPenalty": 1.8737123567344889,
            "drawRegionBigCityScarcityBonus": 7.159461230202946,
            "keepCityPopulationScore": 21.348629225373625,
            "keepCityNetworkProximityScore": 8.634750742616044,
            "keepCityPairCohesionScore": 0,
            "keepCityRegionMatchScore": 3.4350336559737715,
            "keepCityAdjacencyPotentialScore": 4.879891703484787,
            "claimAdjacentNetworkBonus": 11.550841047925253,
            "claimOpponentBlockPenalty": 1.472488754511708
          }
        },
        "candidate": {
          "score": 353662.5833333334,
          "winRate": 0.6666666666666666,
          "averageRank": 1.3333333333333333,
          "averagePassengers": 329127.1666666667,
          "averagePassengerMargin": 21572.916666666668,
          "averageConnectedCities": 19.25,
          "averageMoney": 10706611.9499533,
          "timeoutRate": 0,
          "sampleCount": 12,
          "weights": {
            "vehiclePriorityBus": 62.63740953800401,
            "vehiclePriorityTrain": 152.6422209498406,
            "vehiclePriorityAir": -29.55999851023245,
            "claimRailBaseScore": 60.11959186375494,
            "claimAirBaseScore": 89.63431550977485,
            "claimPopulationPerMillionScore": 6.359629418275925,
            "claimNewCityBonus": 24,
            "claimFirstModeBonus": 18,
            "claimRailCostPenaltyPerMillion": 4.578396180330495,
            "claimPacificPreference": 0,
            "claimMountainPreference": 0,
            "claimSouthPreference": 5.839233425578902,
            "claimSoutheastPreference": 6.7253940512559245,
            "claimMidwestPreference": -0.6176278742828546,
            "claimNortheastPreference": 2.358612009723272,
            "claimSameRegionLinkBonus": -3.938759710207316,
            "claimNewRegionBonus": 0,
            "claimLongDistancePreference": 18.037087754798787,
            "buyBusOwnedCityBonus": 7.664941194725206,
            "buyTrainPotentialClaimBonus": 49.23433214888079,
            "buyTrainFallbackOwnedCityBonus": 3.9234573892982945,
            "buyTrainNoClaimPenalty": 25.26648701215163,
            "buyAirPotentialClaimBonus": 30.77319424361922,
            "buyAirFallbackOwnedCityBonus": 11.388636013958603,
            "buyAirNoClaimPenalty": 39.48746975517964,
            "buyDuplicateVehiclePenalty": 6.26676924876011,
            "buyFirstTrainBonus": 15.459284954937175,
            "buyFirstAirBonus": 26.422247604600017,
            "earlyExpansionMultiplier": 1.45,
            "midExpansionMultiplier": 1.1817034385865557,
            "lateExpansionMultiplier": 0.4528080216908296,
            "earlyPopulationMultiplier": 0.8,
            "midPopulationMultiplier": 0.20740766541101038,
            "latePopulationMultiplier": 1.267599105822488,
            "earlyReadyOperationsScore": 12.092547246853687,
            "midReadyOperationsScore": 143.91187764118825,
            "lateReadyOperationsScore": 228,
            "earlyClaimBudget": 2.519575742675761,
            "midClaimBudget": 4.744340092613403,
            "lateClaimBudget": 0.07760727368295194,
            "podSplitBaseScore": 31.487725528954922,
            "podCityCountScore": 18.337680806861158,
            "podPopulationPerMillionScore": 11.45055799502584,
            "podPopulationPerDistanceScore": 49.95646060727803,
            "podDemandScore": 2.6486545984954804,
            "podDemandPerMileScore": 5.1666648595423865,
            "podNetRevenueScore": 17.912357214439126,
            "podAdditionalRoutePenalty": 5.024643044188509,
            "podRemoveCityBaseScore": 2.6287409673844064,
            "podRemovePassengersPerDistanceGainScore": 21.894760658931254,
            "podRemoveNetRevenueGainScore": 18.569295245355796,
            "drawRegionDeckSizeScore": 0,
            "drawRegionOwnedCityBonus": 9.41416048572014,
            "drawRegionOpponentCityPenalty": 1.8737123567344889,
            "drawRegionBigCityScarcityBonus": 7.1892960475528565,
            "keepCityPopulationScore": 22.147967072904468,
            "keepCityNetworkProximityScore": 8.011031364427792,
            "keepCityPairCohesionScore": 0,
            "keepCityRegionMatchScore": 3.0782475378985197,
            "keepCityAdjacencyPotentialScore": 5.601464528052343,
            "claimAdjacentNetworkBonus": 11.731272063714762,
            "claimOpponentBlockPenalty": 1.9412901232846915
          }
        }
      },
      {
        "iteration": 8,
        "temperature": 0.30000000000000004,
        "best": {
          "score": 405971.5833333334,
          "winRate": 0.5833333333333334,
          "averageRank": 1.4166666666666667,
          "averagePassengers": 345683.9166666667,
          "averagePassengerMargin": 57837.666666666664,
          "averageConnectedCities": 19,
          "averageMoney": 9131192.912387757,
          "timeoutRate": 0,
          "sampleCount": 12,
          "weights": {
            "vehiclePriorityBus": 56.92069311400076,
            "vehiclePriorityTrain": 147.6270636320979,
            "vehiclePriorityAir": -33.72638851461399,
            "claimRailBaseScore": 61.464493784609985,
            "claimAirBaseScore": 97.13751584557549,
            "claimPopulationPerMillionScore": 6.288080105598691,
            "claimNewCityBonus": 24,
            "claimFirstModeBonus": 18,
            "claimRailCostPenaltyPerMillion": 4.307945913321058,
            "claimPacificPreference": 0,
            "claimMountainPreference": 0,
            "claimSouthPreference": 5.839233425578902,
            "claimSoutheastPreference": 6.7253940512559245,
            "claimMidwestPreference": -0.6176278742828546,
            "claimNortheastPreference": 2.358612009723272,
            "claimSameRegionLinkBonus": -3.938759710207316,
            "claimNewRegionBonus": 0,
            "claimLongDistancePreference": 14.919571553064243,
            "buyBusOwnedCityBonus": 7.716007420864871,
            "buyTrainPotentialClaimBonus": 51.68084059856934,
            "buyTrainFallbackOwnedCityBonus": 3.9234573892982945,
            "buyTrainNoClaimPenalty": 25.26648701215163,
            "buyAirPotentialClaimBonus": 28.42695048809983,
            "buyAirFallbackOwnedCityBonus": 11.388636013958603,
            "buyAirNoClaimPenalty": 39.48746975517964,
            "buyDuplicateVehiclePenalty": 6.366012846446401,
            "buyFirstTrainBonus": 15.459284954937175,
            "buyFirstAirBonus": 26.422247604600017,
            "earlyExpansionMultiplier": 1.45,
            "midExpansionMultiplier": 1.1817034385865557,
            "lateExpansionMultiplier": 0.4528080216908296,
            "earlyPopulationMultiplier": 0.8,
            "midPopulationMultiplier": 0.27691409648396076,
            "latePopulationMultiplier": 1.267599105822488,
            "earlyReadyOperationsScore": 12.092547246853687,
            "midReadyOperationsScore": 143.91187764118825,
            "lateReadyOperationsScore": 228,
            "earlyClaimBudget": 2.188568762733439,
            "midClaimBudget": 5.1174798648050475,
            "lateClaimBudget": 0,
            "podSplitBaseScore": 31.487725528954922,
            "podCityCountScore": 17.700414639607903,
            "podPopulationPerMillionScore": 11.728738037680115,
            "podPopulationPerDistanceScore": 50.2512889808443,
            "podDemandScore": 2.2194584363461702,
            "podDemandPerMileScore": 5.930336809420722,
            "podNetRevenueScore": 17.912357214439126,
            "podAdditionalRoutePenalty": 5.394748211666832,
            "podRemoveCityBaseScore": 2.6287409673844064,
            "podRemovePassengersPerDistanceGainScore": 21.894760658931254,
            "podRemoveNetRevenueGainScore": 18.569295245355796,
            "drawRegionDeckSizeScore": 0,
            "drawRegionOwnedCityBonus": 10.027028334295256,
            "drawRegionOpponentCityPenalty": 1.8737123567344889,
            "drawRegionBigCityScarcityBonus": 7.159461230202946,
            "keepCityPopulationScore": 21.348629225373625,
            "keepCityNetworkProximityScore": 8.634750742616044,
            "keepCityPairCohesionScore": 0,
            "keepCityRegionMatchScore": 3.4350336559737715,
            "keepCityAdjacencyPotentialScore": 4.879891703484787,
            "claimAdjacentNetworkBonus": 11.550841047925253,
            "claimOpponentBlockPenalty": 1.472488754511708
          }
        },
        "candidate": {
          "score": 405971.5833333334,
          "winRate": 0.5833333333333334,
          "averageRank": 1.4166666666666667,
          "averagePassengers": 345683.9166666667,
          "averagePassengerMargin": 57837.666666666664,
          "averageConnectedCities": 19,
          "averageMoney": 9131192.912387757,
          "timeoutRate": 0,
          "sampleCount": 12,
          "weights": {
            "vehiclePriorityBus": 57.77599269428423,
            "vehiclePriorityTrain": 147.9930971300163,
            "vehiclePriorityAir": -31.814651242656886,
            "claimRailBaseScore": 65.07385551549847,
            "claimAirBaseScore": 104.0426710792418,
            "claimPopulationPerMillionScore": 6.132072479388351,
            "claimNewCityBonus": 24,
            "claimFirstModeBonus": 18,
            "claimRailCostPenaltyPerMillion": 4.334519329166691,
            "claimPacificPreference": 0,
            "claimMountainPreference": 0,
            "claimSouthPreference": 5.839233425578902,
            "claimSoutheastPreference": 6.7253940512559245,
            "claimMidwestPreference": -0.6176278742828546,
            "claimNortheastPreference": 2.358612009723272,
            "claimSameRegionLinkBonus": -3.938759710207316,
            "claimNewRegionBonus": 0,
            "claimLongDistancePreference": 16.699843197209493,
            "buyBusOwnedCityBonus": 8.042851431646367,
            "buyTrainPotentialClaimBonus": 48.34529715968398,
            "buyTrainFallbackOwnedCityBonus": 3.9234573892982945,
            "buyTrainNoClaimPenalty": 25.26648701215163,
            "buyAirPotentialClaimBonus": 29.935573153337465,
            "buyAirFallbackOwnedCityBonus": 11.388636013958603,
            "buyAirNoClaimPenalty": 39.48746975517964,
            "buyDuplicateVehiclePenalty": 7.450762725575633,
            "buyFirstTrainBonus": 15.459284954937175,
            "buyFirstAirBonus": 26.422247604600017,
            "earlyExpansionMultiplier": 1.45,
            "midExpansionMultiplier": 1.1817034385865557,
            "lateExpansionMultiplier": 0.4528080216908296,
            "earlyPopulationMultiplier": 0.8,
            "midPopulationMultiplier": 0.27790787355974317,
            "latePopulationMultiplier": 1.267599105822488,
            "earlyReadyOperationsScore": 12.092547246853687,
            "midReadyOperationsScore": 143.91187764118825,
            "lateReadyOperationsScore": 228,
            "earlyClaimBudget": 2.1776607187900936,
            "midClaimBudget": 4.934960708924611,
            "lateClaimBudget": 0,
            "podSplitBaseScore": 31.487725528954922,
            "podCityCountScore": 18.41873444811338,
            "podPopulationPerMillionScore": 11.351608403955426,
            "podPopulationPerDistanceScore": 50.00575587623088,
            "podDemandScore": 1.9185390677857441,
            "podDemandPerMileScore": 5.855440722668307,
            "podNetRevenueScore": 17.912357214439126,
            "podAdditionalRoutePenalty": 4.916017311267446,
            "podRemoveCityBaseScore": 2.6287409673844064,
            "podRemovePassengersPerDistanceGainScore": 21.894760658931254,
            "podRemoveNetRevenueGainScore": 18.569295245355796,
            "drawRegionDeckSizeScore": 0,
            "drawRegionOwnedCityBonus": 9.708537420039875,
            "drawRegionOpponentCityPenalty": 1.8737123567344889,
            "drawRegionBigCityScarcityBonus": 6.688012394006732,
            "keepCityPopulationScore": 21.403159135628847,
            "keepCityNetworkProximityScore": 8.651738513411866,
            "keepCityPairCohesionScore": 0,
            "keepCityRegionMatchScore": 2.902346986687431,
            "keepCityAdjacencyPotentialScore": 4.959799963815344,
            "claimAdjacentNetworkBonus": 10.711108429155622,
            "claimOpponentBlockPenalty": 1.175351089228773
          }
        }
      },
      {
        "iteration": 9,
        "temperature": 0.2,
        "best": {
          "score": 405971.5833333334,
          "winRate": 0.5833333333333334,
          "averageRank": 1.4166666666666667,
          "averagePassengers": 345683.9166666667,
          "averagePassengerMargin": 57837.666666666664,
          "averageConnectedCities": 19,
          "averageMoney": 9131192.912387757,
          "timeoutRate": 0,
          "sampleCount": 12,
          "weights": {
            "vehiclePriorityBus": 56.92069311400076,
            "vehiclePriorityTrain": 147.6270636320979,
            "vehiclePriorityAir": -33.72638851461399,
            "claimRailBaseScore": 61.464493784609985,
            "claimAirBaseScore": 97.13751584557549,
            "claimPopulationPerMillionScore": 6.288080105598691,
            "claimNewCityBonus": 24,
            "claimFirstModeBonus": 18,
            "claimRailCostPenaltyPerMillion": 4.307945913321058,
            "claimPacificPreference": 0,
            "claimMountainPreference": 0,
            "claimSouthPreference": 5.839233425578902,
            "claimSoutheastPreference": 6.7253940512559245,
            "claimMidwestPreference": -0.6176278742828546,
            "claimNortheastPreference": 2.358612009723272,
            "claimSameRegionLinkBonus": -3.938759710207316,
            "claimNewRegionBonus": 0,
            "claimLongDistancePreference": 14.919571553064243,
            "buyBusOwnedCityBonus": 7.716007420864871,
            "buyTrainPotentialClaimBonus": 51.68084059856934,
            "buyTrainFallbackOwnedCityBonus": 3.9234573892982945,
            "buyTrainNoClaimPenalty": 25.26648701215163,
            "buyAirPotentialClaimBonus": 28.42695048809983,
            "buyAirFallbackOwnedCityBonus": 11.388636013958603,
            "buyAirNoClaimPenalty": 39.48746975517964,
            "buyDuplicateVehiclePenalty": 6.366012846446401,
            "buyFirstTrainBonus": 15.459284954937175,
            "buyFirstAirBonus": 26.422247604600017,
            "earlyExpansionMultiplier": 1.45,
            "midExpansionMultiplier": 1.1817034385865557,
            "lateExpansionMultiplier": 0.4528080216908296,
            "earlyPopulationMultiplier": 0.8,
            "midPopulationMultiplier": 0.27691409648396076,
            "latePopulationMultiplier": 1.267599105822488,
            "earlyReadyOperationsScore": 12.092547246853687,
            "midReadyOperationsScore": 143.91187764118825,
            "lateReadyOperationsScore": 228,
            "earlyClaimBudget": 2.188568762733439,
            "midClaimBudget": 5.1174798648050475,
            "lateClaimBudget": 0,
            "podSplitBaseScore": 31.487725528954922,
            "podCityCountScore": 17.700414639607903,
            "podPopulationPerMillionScore": 11.728738037680115,
            "podPopulationPerDistanceScore": 50.2512889808443,
            "podDemandScore": 2.2194584363461702,
            "podDemandPerMileScore": 5.930336809420722,
            "podNetRevenueScore": 17.912357214439126,
            "podAdditionalRoutePenalty": 5.394748211666832,
            "podRemoveCityBaseScore": 2.6287409673844064,
            "podRemovePassengersPerDistanceGainScore": 21.894760658931254,
            "podRemoveNetRevenueGainScore": 18.569295245355796,
            "drawRegionDeckSizeScore": 0,
            "drawRegionOwnedCityBonus": 10.027028334295256,
            "drawRegionOpponentCityPenalty": 1.8737123567344889,
            "drawRegionBigCityScarcityBonus": 7.159461230202946,
            "keepCityPopulationScore": 21.348629225373625,
            "keepCityNetworkProximityScore": 8.634750742616044,
            "keepCityPairCohesionScore": 0,
            "keepCityRegionMatchScore": 3.4350336559737715,
            "keepCityAdjacencyPotentialScore": 4.879891703484787,
            "claimAdjacentNetworkBonus": 11.550841047925253,
            "claimOpponentBlockPenalty": 1.472488754511708
          }
        },
        "candidate": {
          "score": 364054.8333333333,
          "winRate": 0.4166666666666667,
          "averageRank": 1.5833333333333333,
          "averagePassengers": 360071.5,
          "averagePassengerMargin": 2545.8333333333335,
          "averageConnectedCities": 18.75,
          "averageMoney": 10478684.726426696,
          "timeoutRate": 0,
          "sampleCount": 12,
          "weights": {
            "vehiclePriorityBus": 60.11207914312502,
            "vehiclePriorityTrain": 144.73526591127074,
            "vehiclePriorityAir": -36.38199202438283,
            "claimRailBaseScore": 66.16126781955714,
            "claimAirBaseScore": 97.62770329830902,
            "claimPopulationPerMillionScore": 5.815058511024016,
            "claimNewCityBonus": 24,
            "claimFirstModeBonus": 18,
            "claimRailCostPenaltyPerMillion": 4.200682989007513,
            "claimPacificPreference": 0,
            "claimMountainPreference": 0,
            "claimSouthPreference": 5.839233425578902,
            "claimSoutheastPreference": 6.7253940512559245,
            "claimMidwestPreference": -0.6176278742828546,
            "claimNortheastPreference": 2.358612009723272,
            "claimSameRegionLinkBonus": -3.938759710207316,
            "claimNewRegionBonus": 0,
            "claimLongDistancePreference": 16.12935352165784,
            "buyBusOwnedCityBonus": 7.833905285854808,
            "buyTrainPotentialClaimBonus": 52.061235199646184,
            "buyTrainFallbackOwnedCityBonus": 3.9234573892982945,
            "buyTrainNoClaimPenalty": 25.26648701215163,
            "buyAirPotentialClaimBonus": 30.45924569484778,
            "buyAirFallbackOwnedCityBonus": 11.388636013958603,
            "buyAirNoClaimPenalty": 39.48746975517964,
            "buyDuplicateVehiclePenalty": 6.536095703906185,
            "buyFirstTrainBonus": 15.459284954937175,
            "buyFirstAirBonus": 26.422247604600017,
            "earlyExpansionMultiplier": 1.45,
            "midExpansionMultiplier": 1.1817034385865557,
            "lateExpansionMultiplier": 0.4528080216908296,
            "earlyPopulationMultiplier": 0.8,
            "midPopulationMultiplier": 0.2837515533808619,
            "latePopulationMultiplier": 1.267599105822488,
            "earlyReadyOperationsScore": 12.092547246853687,
            "midReadyOperationsScore": 143.91187764118825,
            "lateReadyOperationsScore": 228,
            "earlyClaimBudget": 2.0975454891536627,
            "midClaimBudget": 5.2570212491965345,
            "lateClaimBudget": 0.16446825601160528,
            "podSplitBaseScore": 31.487725528954922,
            "podCityCountScore": 18.488025519893405,
            "podPopulationPerMillionScore": 11.745710257996643,
            "podPopulationPerDistanceScore": 50.457593626941424,
            "podDemandScore": 2.2238655115333614,
            "podDemandPerMileScore": 6.271307444276052,
            "podNetRevenueScore": 17.912357214439126,
            "podAdditionalRoutePenalty": 5.659928306952009,
            "podRemoveCityBaseScore": 2.6287409673844064,
            "podRemovePassengersPerDistanceGainScore": 21.894760658931254,
            "podRemoveNetRevenueGainScore": 18.569295245355796,
            "drawRegionDeckSizeScore": 0.08521266561001539,
            "drawRegionOwnedCityBonus": 10.203888653559488,
            "drawRegionOpponentCityPenalty": 1.8737123567344889,
            "drawRegionBigCityScarcityBonus": 6.94909717121664,
            "keepCityPopulationScore": 21.404809644215167,
            "keepCityNetworkProximityScore": 8.89796934627174,
            "keepCityPairCohesionScore": 0,
            "keepCityRegionMatchScore": 3.0902575558672343,
            "keepCityAdjacencyPotentialScore": 4.9753627866713535,
            "claimAdjacentNetworkBonus": 11.130288548519214,
            "claimOpponentBlockPenalty": 1.1222172844120204
          }
        }
      },
      {
        "iteration": 10,
        "temperature": 0.2,
        "best": {
          "score": 405971.5833333334,
          "winRate": 0.5833333333333334,
          "averageRank": 1.4166666666666667,
          "averagePassengers": 345683.9166666667,
          "averagePassengerMargin": 57837.666666666664,
          "averageConnectedCities": 19,
          "averageMoney": 9131192.912387757,
          "timeoutRate": 0,
          "sampleCount": 12,
          "weights": {
            "vehiclePriorityBus": 56.92069311400076,
            "vehiclePriorityTrain": 147.6270636320979,
            "vehiclePriorityAir": -33.72638851461399,
            "claimRailBaseScore": 61.464493784609985,
            "claimAirBaseScore": 97.13751584557549,
            "claimPopulationPerMillionScore": 6.288080105598691,
            "claimNewCityBonus": 24,
            "claimFirstModeBonus": 18,
            "claimRailCostPenaltyPerMillion": 4.307945913321058,
            "claimPacificPreference": 0,
            "claimMountainPreference": 0,
            "claimSouthPreference": 5.839233425578902,
            "claimSoutheastPreference": 6.7253940512559245,
            "claimMidwestPreference": -0.6176278742828546,
            "claimNortheastPreference": 2.358612009723272,
            "claimSameRegionLinkBonus": -3.938759710207316,
            "claimNewRegionBonus": 0,
            "claimLongDistancePreference": 14.919571553064243,
            "buyBusOwnedCityBonus": 7.716007420864871,
            "buyTrainPotentialClaimBonus": 51.68084059856934,
            "buyTrainFallbackOwnedCityBonus": 3.9234573892982945,
            "buyTrainNoClaimPenalty": 25.26648701215163,
            "buyAirPotentialClaimBonus": 28.42695048809983,
            "buyAirFallbackOwnedCityBonus": 11.388636013958603,
            "buyAirNoClaimPenalty": 39.48746975517964,
            "buyDuplicateVehiclePenalty": 6.366012846446401,
            "buyFirstTrainBonus": 15.459284954937175,
            "buyFirstAirBonus": 26.422247604600017,
            "earlyExpansionMultiplier": 1.45,
            "midExpansionMultiplier": 1.1817034385865557,
            "lateExpansionMultiplier": 0.4528080216908296,
            "earlyPopulationMultiplier": 0.8,
            "midPopulationMultiplier": 0.27691409648396076,
            "latePopulationMultiplier": 1.267599105822488,
            "earlyReadyOperationsScore": 12.092547246853687,
            "midReadyOperationsScore": 143.91187764118825,
            "lateReadyOperationsScore": 228,
            "earlyClaimBudget": 2.188568762733439,
            "midClaimBudget": 5.1174798648050475,
            "lateClaimBudget": 0,
            "podSplitBaseScore": 31.487725528954922,
            "podCityCountScore": 17.700414639607903,
            "podPopulationPerMillionScore": 11.728738037680115,
            "podPopulationPerDistanceScore": 50.2512889808443,
            "podDemandScore": 2.2194584363461702,
            "podDemandPerMileScore": 5.930336809420722,
            "podNetRevenueScore": 17.912357214439126,
            "podAdditionalRoutePenalty": 5.394748211666832,
            "podRemoveCityBaseScore": 2.6287409673844064,
            "podRemovePassengersPerDistanceGainScore": 21.894760658931254,
            "podRemoveNetRevenueGainScore": 18.569295245355796,
            "drawRegionDeckSizeScore": 0,
            "drawRegionOwnedCityBonus": 10.027028334295256,
            "drawRegionOpponentCityPenalty": 1.8737123567344889,
            "drawRegionBigCityScarcityBonus": 7.159461230202946,
            "keepCityPopulationScore": 21.348629225373625,
            "keepCityNetworkProximityScore": 8.634750742616044,
            "keepCityPairCohesionScore": 0,
            "keepCityRegionMatchScore": 3.4350336559737715,
            "keepCityAdjacencyPotentialScore": 4.879891703484787,
            "claimAdjacentNetworkBonus": 11.550841047925253,
            "claimOpponentBlockPenalty": 1.472488754511708
          }
        },
        "candidate": {
          "score": 351747.25,
          "winRate": 0.4166666666666667,
          "averageRank": 1.5833333333333333,
          "averagePassengers": 353879.8333333333,
          "averagePassengerMargin": -3570.0833333333335,
          "averageConnectedCities": 18.75,
          "averageMoney": 10691218.069984118,
          "timeoutRate": 0,
          "sampleCount": 12,
          "weights": {
            "vehiclePriorityBus": 55.15511015390178,
            "vehiclePriorityTrain": 146.52226184615202,
            "vehiclePriorityAir": -31.46423770712155,
            "claimRailBaseScore": 60.68349463224764,
            "claimAirBaseScore": 92.58939774898545,
            "claimPopulationPerMillionScore": 5.968162757152366,
            "claimNewCityBonus": 24,
            "claimFirstModeBonus": 18,
            "claimRailCostPenaltyPerMillion": 4.131349913461785,
            "claimPacificPreference": 0,
            "claimMountainPreference": 0,
            "claimSouthPreference": 5.839233425578902,
            "claimSoutheastPreference": 6.7253940512559245,
            "claimMidwestPreference": -0.6176278742828546,
            "claimNortheastPreference": 2.358612009723272,
            "claimSameRegionLinkBonus": -3.938759710207316,
            "claimNewRegionBonus": 0,
            "claimLongDistancePreference": 15.409660292310372,
            "buyBusOwnedCityBonus": 8.068638914895228,
            "buyTrainPotentialClaimBonus": 50.670507481657985,
            "buyTrainFallbackOwnedCityBonus": 3.9234573892982945,
            "buyTrainNoClaimPenalty": 25.26648701215163,
            "buyAirPotentialClaimBonus": 29.21400610157289,
            "buyAirFallbackOwnedCityBonus": 11.388636013958603,
            "buyAirNoClaimPenalty": 39.48746975517964,
            "buyDuplicateVehiclePenalty": 5.651439416548974,
            "buyFirstTrainBonus": 15.459284954937175,
            "buyFirstAirBonus": 26.422247604600017,
            "earlyExpansionMultiplier": 1.45,
            "midExpansionMultiplier": 1.1817034385865557,
            "lateExpansionMultiplier": 0.4528080216908296,
            "earlyPopulationMultiplier": 0.8,
            "midPopulationMultiplier": 0.25153901332058015,
            "latePopulationMultiplier": 1.267599105822488,
            "earlyReadyOperationsScore": 12.092547246853687,
            "midReadyOperationsScore": 143.91187764118825,
            "lateReadyOperationsScore": 228,
            "earlyClaimBudget": 2.0066082850534714,
            "midClaimBudget": 5.080481146852528,
            "lateClaimBudget": 0.05479568745940924,
            "podSplitBaseScore": 31.487725528954922,
            "podCityCountScore": 17.2761617201277,
            "podPopulationPerMillionScore": 11.360397450250412,
            "podPopulationPerDistanceScore": 49.8701093953502,
            "podDemandScore": 2.1157747594495535,
            "podDemandPerMileScore": 6.023612107226389,
            "podNetRevenueScore": 17.912357214439126,
            "podAdditionalRoutePenalty": 5.364826338752995,
            "podRemoveCityBaseScore": 2.6287409673844064,
            "podRemovePassengersPerDistanceGainScore": 21.894760658931254,
            "podRemoveNetRevenueGainScore": 18.569295245355796,
            "drawRegionDeckSizeScore": 0.11743380231782795,
            "drawRegionOwnedCityBonus": 10.276516030324501,
            "drawRegionOpponentCityPenalty": 1.8737123567344889,
            "drawRegionBigCityScarcityBonus": 7.53135457949284,
            "keepCityPopulationScore": 21.06239308170265,
            "keepCityNetworkProximityScore": 8.61736842502086,
            "keepCityPairCohesionScore": 0,
            "keepCityRegionMatchScore": 3.8039843509594595,
            "keepCityAdjacencyPotentialScore": 5.259697460403872,
            "claimAdjacentNetworkBonus": 11.244685244963815,
            "claimOpponentBlockPenalty": 1.2104075035908162
          }
        }
      }
    ],
    "final": {
      "score": 405971.5833333334,
      "winRate": 0.5833333333333334,
      "averageRank": 1.4166666666666667,
      "averagePassengers": 345683.9166666667,
      "averagePassengerMargin": 57837.666666666664,
      "averageConnectedCities": 19,
      "averageMoney": 9131192.912387757,
      "timeoutRate": 0,
      "sampleCount": 12,
      "weights": {
        "vehiclePriorityBus": 56.92069311400076,
        "vehiclePriorityTrain": 147.6270636320979,
        "vehiclePriorityAir": -33.72638851461399,
        "claimRailBaseScore": 61.464493784609985,
        "claimAirBaseScore": 97.13751584557549,
        "claimPopulationPerMillionScore": 6.288080105598691,
        "claimNewCityBonus": 24,
        "claimFirstModeBonus": 18,
        "claimRailCostPenaltyPerMillion": 4.307945913321058,
        "claimPacificPreference": 0,
        "claimMountainPreference": 0,
        "claimSouthPreference": 5.839233425578902,
        "claimSoutheastPreference": 6.7253940512559245,
        "claimMidwestPreference": -0.6176278742828546,
        "claimNortheastPreference": 2.358612009723272,
        "claimSameRegionLinkBonus": -3.938759710207316,
        "claimNewRegionBonus": 0,
        "claimLongDistancePreference": 14.919571553064243,
        "buyBusOwnedCityBonus": 7.716007420864871,
        "buyTrainPotentialClaimBonus": 51.68084059856934,
        "buyTrainFallbackOwnedCityBonus": 3.9234573892982945,
        "buyTrainNoClaimPenalty": 25.26648701215163,
        "buyAirPotentialClaimBonus": 28.42695048809983,
        "buyAirFallbackOwnedCityBonus": 11.388636013958603,
        "buyAirNoClaimPenalty": 39.48746975517964,
        "buyDuplicateVehiclePenalty": 6.366012846446401,
        "buyFirstTrainBonus": 15.459284954937175,
        "buyFirstAirBonus": 26.422247604600017,
        "earlyExpansionMultiplier": 1.45,
        "midExpansionMultiplier": 1.1817034385865557,
        "lateExpansionMultiplier": 0.4528080216908296,
        "earlyPopulationMultiplier": 0.8,
        "midPopulationMultiplier": 0.27691409648396076,
        "latePopulationMultiplier": 1.267599105822488,
        "earlyReadyOperationsScore": 12.092547246853687,
        "midReadyOperationsScore": 143.91187764118825,
        "lateReadyOperationsScore": 228,
        "earlyClaimBudget": 2.188568762733439,
        "midClaimBudget": 5.1174798648050475,
        "lateClaimBudget": 0,
        "podSplitBaseScore": 31.487725528954922,
        "podCityCountScore": 17.700414639607903,
        "podPopulationPerMillionScore": 11.728738037680115,
        "podPopulationPerDistanceScore": 50.2512889808443,
        "podDemandScore": 2.2194584363461702,
        "podDemandPerMileScore": 5.930336809420722,
        "podNetRevenueScore": 17.912357214439126,
        "podAdditionalRoutePenalty": 5.394748211666832,
        "podRemoveCityBaseScore": 2.6287409673844064,
        "podRemovePassengersPerDistanceGainScore": 21.894760658931254,
        "podRemoveNetRevenueGainScore": 18.569295245355796,
        "drawRegionDeckSizeScore": 0,
        "drawRegionOwnedCityBonus": 10.027028334295256,
        "drawRegionOpponentCityPenalty": 1.8737123567344889,
        "drawRegionBigCityScarcityBonus": 7.159461230202946,
        "keepCityPopulationScore": 21.348629225373625,
        "keepCityNetworkProximityScore": 8.634750742616044,
        "keepCityPairCohesionScore": 0,
        "keepCityRegionMatchScore": 3.4350336559737715,
        "keepCityAdjacencyPotentialScore": 4.879891703484787,
        "claimAdjacentNetworkBonus": 11.550841047925253,
        "claimOpponentBlockPenalty": 1.472488754511708
      }
    }
  }
}